{
  "reference_id": "arion_expected_reference_chat_2026-03-11",
  "scene": "composite_stepped_facade",
  "reference_image_path": "assets\\reference\\arion_expected_reference_chat_2026-03-11.png",
  "image_size": [
    2408,
    1007
  ],
  "targets": {
    "facade_bbox": [
      87,
      168,
      2268,
      641
    ],
    "socle_bbox": [
      88,
      683,
      2277,
      221
    ],
    "facade_contour": [
      [
        2354,
        168
      ],
      [
        2155,
        168
      ],
      [
        2154,
        321
      ],
      [
        1863,
        321
      ],
      [
        1861,
        180
      ],
      [
        1663,
        180
      ],
      [
        1662,
        310
      ],
      [
        1324,
        310
      ],
      [
        1322,
        472
      ],
      [
        87,
        472
      ],
      [
        88,
        808
      ],
      [
        1327,
        808
      ],
      [
        1329,
        684
      ],
      [
        2354,
        684
      ]
    ],
    "socle_contour": [
      [
        2364,
        683
      ],
      [
        2354,
        720
      ],
      [
        91,
        903
      ],
      [
        88,
        809
      ],
      [
        88,
        903
      ],
      [
        2354,
        721
      ]
    ],
    "facade_contour_norm_in_bbox": [
      [
        0.999559,
        0.0
      ],
      [
        0.911817,
        0.0
      ],
      [
        0.911376,
        0.23869
      ],
      [
        0.783069,
        0.23869
      ],
      [
        0.782187,
        0.018721
      ],
      [
        0.694885,
        0.018721
      ],
      [
        0.694444,
        0.221529
      ],
      [
        0.545414,
        0.221529
      ],
      [
        0.544533,
        0.474259
      ],
      [
        0.0,
        0.474259
      ],
      [
        0.000441,
        0.99844
      ],
      [
        0.546737,
        0.99844
      ],
      [
        0.547619,
        0.804992
      ],
      [
        0.999559,
        0.804992
      ]
    ],
    "socle_contour_norm_in_facade_bbox": [
      [
        1.003968,
        0.803432
      ],
      [
        0.999559,
        0.861154
      ],
      [
        0.001764,
        1.146646
      ],
      [
        0.000441,
        1.0
      ],
      [
        0.000441,
        1.146646
      ],
      [
        0.999559,
        0.862715
      ]
    ],
    "window_boxes": [
      [
        185,
        587,
        182,
        129
      ],
      [
        489,
        586,
        51,
        127
      ],
      [
        662,
        586,
        44,
        125
      ],
      [
        858,
        585,
        185,
        127
      ],
      [
        1511,
        446,
        171,
        133
      ],
      [
        2008,
        435,
        164,
        131
      ]
    ],
    "door_boxes": [
      [
        538,
        586,
        126,
        221
      ],
      [
        1191,
        596,
        126,
        211
      ]
    ],
    "window_boxes_norm_in_facade_bbox": [
      {
        "x": 0.04321,
        "y": 0.653666,
        "w": 0.080247,
        "h": 0.201248
      },
      {
        "x": 0.177249,
        "y": 0.652106,
        "w": 0.022487,
        "h": 0.198128
      },
      {
        "x": 0.253527,
        "y": 0.652106,
        "w": 0.0194,
        "h": 0.195008
      },
      {
        "x": 0.339947,
        "y": 0.650546,
        "w": 0.08157,
        "h": 0.198128
      },
      {
        "x": 0.627866,
        "y": 0.433697,
        "w": 0.075397,
        "h": 0.207488
      },
      {
        "x": 0.847002,
        "y": 0.416537,
        "w": 0.07231,
        "h": 0.204368
      }
    ],
    "door_boxes_norm_in_facade_bbox": [
      {
        "x": 0.198854,
        "y": 0.652106,
        "w": 0.055556,
        "h": 0.344774
      },
      {
        "x": 0.486772,
        "y": 0.667707,
        "w": 0.055556,
        "h": 0.329173
      }
    ]
  }
}